thoth/s2i/__init__.py
thoth/s2i/cli.py
thoth/s2i/exceptions.py
thoth/s2i/helpers.py
thoth/s2i/lib.py
thoth/s2i/objs.py
thoth/s2i/py.typed
thoth_s2i-0.0.0.dist-info/METADATA
thoth_s2i-0.0.0.dist-info/RECORD
thoth_s2i-0.0.0.dist-info/WHEEL
thoth_s2i-0.0.0.dist-info/entry_points.txt
thoth_s2i-0.0.0.dist-info/top_level.txt
