Metadata-Version: 2.1
Name: thoth-s2i
Version: 0.0.0
Summary: Tooling and a library for Thoth's Python Source-To-Image (s2i) applications
Home-page: UNKNOWN
Author: Fridolin Pokorny
Author-email: fridolin@redhat.com
License: GPLv3+
Platform: UNKNOWN
Requires-Dist: click
Requires-Dist: requests
Requires-Dist: daiquiri
Requires-Dist: pyyaml
Requires-Dist: termcolor
Requires-Dist: attrs
